ws_frappe_cli/__init__.py
ws_frappe_cli/main.py
ws_frappe_cli/py.typed
ws_frappe_cli/utils.py
ws_frappe_cli/commands/__init__.py
ws_frappe_cli/commands/create_site.py
ws_frappe_cli/commands/fetch_app.py
ws_frappe_cli/commands/get_apps.py
ws_frappe_cli/commands/setup.py
ws_frappe_cli/commands/shortcuts.py
ws_frappe_cli/templates/__init__.py
ws_frappe_cli/templates/docs/TECHNICAL_DOCS.md
ws_frappe_cli/templates/docs/__init__.py
ws_frappe_cli-1.1.1.dist-info/licenses/LICENSE
ws_frappe_cli-1.1.1.dist-info/METADATA
ws_frappe_cli-1.1.1.dist-info/WHEEL
ws_frappe_cli-1.1.1.dist-info/entry_points.txt
ws_frappe_cli-1.1.1.dist-info/top_level.txt
ws_frappe_cli-1.1.1.dist-info/RECORD
