Metadata-Version: 2.4
Name: ws-frappe-cli
Version: 1.1.1
Summary: A command-line tool for Frappe/ERPNext development environment management
Home-page: https://github.com/whitestork-erp/ws-frappe-cli
Author: HHH
Author-email: HHH <hasanhajhasan98@gmail.com>
Maintainer-email: HHH <hasanhajhasan98@gmail.com>
License: MIT
Project-URL: Homepage, https://github.com/whitestork-erp/ws-frappe-cli
Project-URL: Documentation, https://github.com/whitestork-erp/ws-frappe-cli#readme
Project-URL: Repository, https://github.com/whitestork-erp/ws-frappe-cli.git
Project-URL: Issues, https://github.com/whitestork-erp/ws-frappe-cli/issues
Project-URL: Changelog, https://github.com/whitestork-erp/ws-frappe-cli/blob/main/CHANGELOG.md
Keywords: frappe,erpnext,cli,development,bench
Classifier: Development Status :: 4 - Beta
Classifier: Intended Audience :: Developers
Classifier: License :: OSI Approved :: MIT License
Classifier: Operating System :: OS Independent
Classifier: Programming Language :: Python :: 3
Classifier: Programming Language :: Python :: 3.8
Classifier: Programming Language :: Python :: 3.9
Classifier: Programming Language :: Python :: 3.10
Classifier: Programming Language :: Python :: 3.11
Classifier: Programming Language :: Python :: 3.12
Classifier: Topic :: Software Development :: Libraries :: Python Modules
Classifier: Topic :: System :: Installation/Setup
Classifier: Topic :: System :: Systems Administration
Classifier: Environment :: Console
Requires-Python: >=3.8
License-File: LICENSE
Requires-Dist: click>=8.0.0
Requires-Dist: rich>=10.0.0
Requires-Dist: requests>=2.25.0
Provides-Extra: dev
Requires-Dist: pytest>=7.0.0; extra == "dev"
Requires-Dist: pytest-cov>=4.0.0; extra == "dev"
Requires-Dist: black>=22.0.0; extra == "dev"
Requires-Dist: isort>=5.10.0; extra == "dev"
Requires-Dist: flake8>=4.0.0; extra == "dev"
Requires-Dist: mypy>=0.950; extra == "dev"
Requires-Dist: pre-commit>=2.17.0; extra == "dev"
Provides-Extra: test
Requires-Dist: pytest>=7.0.0; extra == "test"
Requires-Dist: pytest-cov>=4.0.0; extra == "test"
Requires-Dist: pytest-mock>=3.7.0; extra == "test"
Dynamic: license-file
